aglib/FF.py
aglib/__init__.py
aglib/functions.py
aglib/mcstas_reader.py
aglib/mcstas_runner.py
aglib/peakfinder.py
aglib/res.py
aglib-0.2.3.dist-info/licenses/LICENSE
aglib-0.2.3.dist-info/METADATA
aglib-0.2.3.dist-info/WHEEL
aglib-0.2.3.dist-info/top_level.txt
aglib-0.2.3.dist-info/RECORD
